README
setup.py
harmeet_state.egg-info/PKG-INFO
harmeet_state.egg-info/SOURCES.txt
harmeet_state.egg-info/dependency_links.txt
harmeet_state.egg-info/namespace_packages.txt
harmeet_state.egg-info/not-zip-safe
harmeet_state.egg-info/top_level.txt
src/__init__.py
src/__main__.py
src/state.py