Metadata-Version: 1.0
Name: harmeet-state
Version: 1.0
Summary: state module
Home-page: UNKNOWN
Author: harmeet sethi
Author-email: harmeet.sethi@nokia.com
License: MIT
Platform: UNKNOWN
